coalaip_bigchaindb/__init__.py
coalaip_bigchaindb/plugin.py
coalaip_bigchaindb/utils.py
coalaip_bigchaindb-0.0.1.dist-info/DESCRIPTION.rst
coalaip_bigchaindb-0.0.1.dist-info/METADATA
coalaip_bigchaindb-0.0.1.dist-info/RECORD
coalaip_bigchaindb-0.0.1.dist-info/WHEEL
coalaip_bigchaindb-0.0.1.dist-info/entry_points.txt
coalaip_bigchaindb-0.0.1.dist-info/metadata.json
coalaip_bigchaindb-0.0.1.dist-info/top_level.txt
