Metadata-Version: 2.0
Name: coalaip-bigchaindb
Version: 0.0.1
Summary: BigchainDB ledger plugin for COALA IP's Python reference implementation
Home-page: https://github.com/bigchaindb/pycoalaip-bigchaindb
Author: BigchainDB
Author-email: dev@bigchaindb.com
License: Apache Software License 2.0
Keywords: coalaip,coalaip plugin,bigchaindb
Platform: UNKNOWN
Classifier: Development Status :: 3 - Alpha
Classifier: Intended Audience :: Developers
Classifier: License :: OSI Approved :: Apache Software License
Classifier: Natural Language :: English
Classifier: Programming Language :: Python :: 3
Classifier: Programming Language :: Python :: 3.4
Classifier: Programming Language :: Python :: 3.5
Requires-Dist: bigchaindb-driver (~=0.2.0)
Requires-Dist: coalaip (==0.0.1)
Provides-Extra: dev
Requires-Dist: Sphinx (>=1.4.4); extra == 'dev'
Requires-Dist: bigchaindb (~=0.9.0); extra == 'dev'
Requires-Dist: coverage (>=4.1); extra == 'dev'
Requires-Dist: flake8 (>=2.6.0); extra == 'dev'
Requires-Dist: ipdb; extra == 'dev'
Requires-Dist: ipython; extra == 'dev'
Requires-Dist: pytest (>=3.0.1); extra == 'dev'
Requires-Dist: pytest-cov; extra == 'dev'
Requires-Dist: pytest-mock; extra == 'dev'
Requires-Dist: sphinx-autobuild; extra == 'dev'
Requires-Dist: sphinx-rtd-theme; extra == 'dev'
Requires-Dist: sphinxcontrib-napoleon (>=0.4.4); extra == 'dev'
Requires-Dist: tox (>=2.3.1); extra == 'dev'
Provides-Extra: docs
Requires-Dist: Sphinx (>=1.4.4); extra == 'docs'
Requires-Dist: sphinx-autobuild; extra == 'docs'
Requires-Dist: sphinx-rtd-theme; extra == 'docs'
Requires-Dist: sphinxcontrib-napoleon (>=0.4.4); extra == 'docs'
Provides-Extra: test
Requires-Dist: bigchaindb (~=0.9.0); extra == 'test'
Requires-Dist: coverage (>=4.1); extra == 'test'
Requires-Dist: flake8 (>=2.6.0); extra == 'test'
Requires-Dist: pytest (>=3.0.1); extra == 'test'
Requires-Dist: pytest-cov; extra == 'test'
Requires-Dist: pytest-mock; extra == 'test'
Requires-Dist: tox (>=2.3.1); extra == 'test'
